alu.vhd
library IEEE;
use IEEE.STD_LOGIC_1164.ALL;
use IEEE.NUMERIC_STD.ALL;

entity ALU is
    Port (
        A      : in  STD_LOGIC_VECTOR(7 downto 0);
        B      : in  STD_LOGIC_VECTOR(7 downto 0);
        ALU_Sel: in  STD_LOGIC_VECTOR(2 downto 0);
        ALU_Out: out STD_LOGIC_VECTOR(7 downto 0)
    );
end ALU;

architecture Behavioral of ALU is
begin
    process(A, B, ALU_Sel)
    begin
        case ALU_Sel is
            when "000" => -- Addition
                ALU_Out <= std_logic_vector(unsigned(A) + unsigned(B));
            when "001" => -- Subtraction
                ALU_Out <= std_logic_vector(unsigned(A) - unsigned(B));
            when "010" => -- AND
                ALU_Out <= A and B;
            when "011" => -- OR
                ALU_Out <= A or B;
            when "100" => -- Right Shift
                ALU_Out <= std_logic_vector(shift_right(unsigned(A), 1));
            when "101" => -- Left Shift
                ALU_Out <= std_logic_vector(shift_left(unsigned(A), 1));
            when "110" => -- Increment
                ALU_Out <= std_logic_vector(unsigned(A) + 1);
            when "111" => -- Decrement
                ALU_Out <= std_logic_vector(unsigned(A) - 1);
            when others =>
                ALU_Out <= (others => '0');
        end case;
    end process;
end Behavioral;

tb_alu.vhd
library IEEE;
use IEEE.STD_LOGIC_1164.ALL;

entity tb_ALU is
end tb_ALU;

architecture Behavioral of tb_ALU is
    component ALU is
        Port (
            A      : in  STD_LOGIC_VECTOR(7 downto 0);
            B      : in  STD_LOGIC_VECTOR(7 downto 0);
            ALU_Sel: in  STD_LOGIC_VECTOR(2 downto 0);
            ALU_Out: out STD_LOGIC_VECTOR(7 downto 0)
        );
    end component;

    -- Inputs
    signal A      : STD_LOGIC_VECTOR(7 downto 0) := (others => '0');
    signal B      : STD_LOGIC_VECTOR(7 downto 0) := (others => '0');
    signal ALU_Sel: STD_LOGIC_VECTOR(2 downto 0) := (others => '0');

    -- Outputs
    signal ALU_Out: STD_LOGIC_VECTOR(7 downto 0);

begin
    uut: ALU Port map (
        A      => A,
        B      => B,
        ALU_Sel=> ALU_Sel,
        ALU_Out=> ALU_Out
    );

    stim_proc: process
    begin
        -- Test Addition
        A <= "00000010"; B <= "00000011"; ALU_Sel <= "000"; wait for 100 ns;
        -- Test Subtraction
        A <= "00000100"; B <= "00000010"; ALU_Sel <= "001"; wait for 100 ns;
        -- Test AND
        A <= "00001100"; B <= "00001010"; ALU_Sel <= "010"; wait for 100 ns;
        -- Test OR
        A <= "00001100"; B <= "00001010"; ALU_Sel <= "011"; wait for 100 ns;
        -- Test Right Shift
        A <= "00001100"; ALU_Sel <= "100"; wait for 100 ns;
        -- Test Left Shift
        A <= "00001100"; ALU_Sel <= "101"; wait for 100 ns;
        -- Test Increment
        A <= "00001100"; ALU_Sel <= "110"; wait for 100 ns;
        -- Test Decrement
        A <= "00001100"; ALU_Sel <= "111"; wait for 100 ns;

        wait;
    end process;

end Behavioral;

alu.vcd
$date
  Sun Jun  9 07:26:00 2024
$end
$version
  GHDL v0
$end
$timescale
  1 fs
$end
$scope module standard $end
$upscope $end
$scope module std_logic_1164 $end
$upscope $end
$scope module numeric_std $end
$upscope $end
$scope module tb_alu $end
$var reg 8 ! a[7:0] $end
$var reg 8 " b[7:0] $end
$var reg 3 # alu_sel[2:0] $end
$var reg 8 $ alu_out[7:0] $end
$scope module uut $end
$var reg 8 % a[7:0] $end
$var reg 8 & b[7:0] $end
$var reg 3 ' alu_sel[2:0] $end
$var reg 8 ( alu_out[7:0] $end
$upscope $end
$upscope $end
$enddefinitions $end
#0
b00000010 !
b00000011 "
b000 #
b00000101 $
b00000010 %
b00000011 &
b000 '
b00000101 (
#100000000
b00000100 !
b00000010 "
b001 #
b00000010 $
b00000100 %
b00000010 &
b001 '
b00000010 (
#200000000
b00001100 !
b00001010 "
b010 #
b00001000 $
b00001100 %
b00001010 &
b010 '
b00001000 (
#300000000
b011 #
b00001110 $
b011 '
b00001110 (
#400000000
b100 #
b00000110 $
b100 '
b00000110 (
#500000000
b101 #
b00011000 $
b101 '
b00011000 (
#600000000
b110 #
b00001101 $
b110 '
b00001101 (
#700000000
b111 #
b00001011 $
b111 '
b00001011 (
